daiquiri_ui/__init__.py
daiquiri_ui/static/chime.mp3
daiquiri_ui/static/droplet.mp3
daiquiri_ui/static/example.svg
daiquiri_ui/static/favicon.ico
daiquiri_ui/static/index.html
daiquiri_ui/static/manifest.json
daiquiri_ui/static/meta.json
daiquiri_ui/static/assets/Anchor-f3716b7b.js
daiquiri_ui/static/assets/AutoscaleOption-e2ee098d.js
daiquiri_ui/static/assets/BPMVideoStream-5e8c0121.js
daiquiri_ui/static/assets/CanvasEnhancer-abaa5025.js
daiquiri_ui/static/assets/ConnectUtils-bd734a4a.js
daiquiri_ui/static/assets/Console-4f2397f7.js
daiquiri_ui/static/assets/Console-7bbec2e7.css
daiquiri_ui/static/assets/Cross-80ee2b29.js
daiquiri_ui/static/assets/CrossMarker-cc495eca.js
daiquiri_ui/static/assets/DraggableRect-8e897252.js
daiquiri_ui/static/assets/DropdownButton-9a594aef.js
daiquiri_ui/static/assets/DropdownDetector-705d3a9d.js
daiquiri_ui/static/assets/Editor-b897e35a.js
daiquiri_ui/static/assets/EditorTree-792b2d33.js
daiquiri_ui/static/assets/H5Viewer-6c3d85e4.js
daiquiri_ui/static/assets/H5WebCurvePlot-acd3b964.js
daiquiri_ui/static/assets/HSegment-26c3fd51.js
daiquiri_ui/static/assets/HardwareButton-905ce384.js
daiquiri_ui/static/assets/Hdf5Plot-7b8f8e0f.js
daiquiri_ui/static/assets/HistogramDomainSlider-9c6d3e2d.js
daiquiri_ui/static/assets/Image-c1578ac2.js
daiquiri_ui/static/assets/Label-7daca8b6.js
daiquiri_ui/static/assets/LoadingMessage-072bb4e8.js
daiquiri_ui/static/assets/NewScanButton-3ccc3031.js
daiquiri_ui/static/assets/NewScanButton-ed1679d8.js
daiquiri_ui/static/assets/OptionsProcess-9e8d1dd6.js
daiquiri_ui/static/assets/ParametersList-39837f0d.js
daiquiri_ui/static/assets/QtyHelper-8429914f.js
daiquiri_ui/static/assets/RectRoi-a627d206.js
daiquiri_ui/static/assets/RulerButton-ebbb7ca3.js
daiquiri_ui/static/assets/SampleDCList-03813f5f.js
daiquiri_ui/static/assets/SampleRegistration-6fad78fb.js
daiquiri_ui/static/assets/SavingButton-a220fa1e.js
daiquiri_ui/static/assets/ScanPlot0d-c78ff27c.js
daiquiri_ui/static/assets/ScanPlot0dValue-daa69216.js
daiquiri_ui-2025.12.5.dist-info/licenses/LICENSE
daiquiri_ui-2025.12.5.dist-info/METADATA
daiquiri_ui-2025.12.5.dist-info/WHEEL
daiquiri_ui-2025.12.5.dist-info/top_level.txt
daiquiri_ui-2025.12.5.dist-info/RECORD
