Metadata-Version: 2.4
Name: daiquiri-ui
Version: 2025.12.5
Summary: Daiquiri UI
Author-email: ESRF <bcu@esrf.fr>
License-Expression: MIT
Project-URL: Repository, https://gitlab.esrf.fr/ui/daiquiri-ui
Classifier: Intended Audience :: Science/Research
Classifier: Programming Language :: Python :: 3
Requires-Python: >=3.8
License-File: LICENSE
Dynamic: license-file
